filefield_cache/__init__.py
filefield_cache/cache.py
filefield_cache/widgets.py
filefield_cache/templates/filefield_cache/cached_clearable_file_input.html
filefield_cache-0.0.5.dist-info/METADATA
filefield_cache-0.0.5.dist-info/WHEEL
filefield_cache-0.0.5.dist-info/top_level.txt
filefield_cache-0.0.5.dist-info/RECORD
