Metadata-Version: 2.1
Name: filefield-cache
Version: 0.0.5
Summary: Cache Files in Form for files retaining
Home-page: https://github.com/MaistrenkoAnton/
Author: Anton Maistrenko
Author-email: it2015maistrenko@gmail.com
License: MIT License
Platform: UNKNOWN
Classifier: Programming Language :: Python :: 3.6
Classifier: Programming Language :: Python :: 3.7
Classifier: Framework :: Django :: 3.0
Classifier: License :: OSI Approved :: MIT License
Classifier: Operating System :: OS Independent
